smart_arrays/__init__.py
smart_arrays/smart_arrays.py
smart_arrays/smart_arrays_base.py
smart_arrays/stats.py
smart_arrays/uncertainties_arrays.py
smart_arrays/utils.py
smart_arrays-0.0.1.dist-info/METADATA
smart_arrays-0.0.1.dist-info/WHEEL
smart_arrays-0.0.1.dist-info/licenses/LICENSE
smart_arrays-0.0.1.dist-info/RECORD
