Metadata-Version: 2.3
Name: smart_arrays
Version: 0.0.1
Summary: A wrapper around python lists that implement type safety and element-wise operations like numpy. Additionally, if the uncertainties package is installed, arrays of ufloats can be used
Project-URL: Homepage, https://github.com/lautisilber/smart_arrays
Project-URL: Source, https://github.com/lautisilber/smart_arrays
Author-email: Lautaro Silbergleit <lautisilbergleit@gmail.com>
License-Expression: MIT
License-File: LICENSE
Keywords: arrays,numpy,science,typed
Classifier: Intended Audience :: Science/Research
Classifier: License :: OSI Approved :: MIT License
Classifier: Operating System :: OS Independent
Classifier: Programming Language :: Python :: 3
Classifier: Topic :: Scientific/Engineering
Classifier: Topic :: Scientific/Engineering :: Physics
Classifier: Typing :: Typed
Requires-Python: >=3.8
Requires-Dist: future==1.0.0
Requires-Dist: typing-extensions>=4.11
Provides-Extra: uncertainties
Requires-Dist: uncertainties>=3.1; extra == 'uncertainties'
